phases/__init__.py
phases/__main__.py
phases/cli.py
phases/commands/__init__.py
phases/commands/base.py
phases/commands/create.py
phases/generate-template/.gitlab-ci.yml.mustache
phases/generate-template/docker-compose.yml.mustache
phases/generate-template/Dockerfile.mustache
phases/generate-template/docs/sequence.md.mustache
phases/generate-template/packages.m
phases/generate-template/README.md.mustache
phases/generate-template/setup.py.mustache
phases/generate-template/{{name}}/__init__.py.mustache
phases/generate-template/{{name}}/__main__.py.mustache
phases/generate-template/{{name}}/exporter.mustache
phases/generate-template/{{name}}/phases.mustache
phases/generate-template/{{name}}/publisher.mustache
phases/generate-template/{{name}}/storage.mustache
phases/static-template/.editorconfig
phases/static-template/.gitignore
phases/static-template/requirements.txt
phases/util/__init__.py
phases/util/Logger.py
phases/util/Singleton.py
phases-0.1.1.dist-info/entry_points.txt
phases-0.1.1.dist-info/LICENSE
phases-0.1.1.dist-info/WHEEL
phases-0.1.1.dist-info/METADATA
phases-0.1.1.dist-info/RECORD
