Metadata-Version: 2.1
Name: phases
Version: 0.1.1
Summary: A Framework for creating a boilerplate template for ai projects that are ready for MLOps
Home-page: https://gitlab.com/tud.ibmt/phases
License: MIT
Author: fehrlich
Author-email: fehrlichd@gmail.com
Requires-Python: >=3.7,<4.0
Classifier: License :: OSI Approved :: MIT License
Classifier: Programming Language :: Python :: 3
Classifier: Programming Language :: Python :: 3.7
Classifier: Programming Language :: Python :: 3.8
Requires-Dist: PyYAML (>=5.3,<6.0)
Requires-Dist: docopt (>=0.6,<0.7)
Requires-Dist: pyPhases (>=0.0,<0.1)
Requires-Dist: pystache (>=0.5,<0.6)
Project-URL: Repository, https://gitlab.com/tud.ibmt/phases
